byuhbll_django_dry/__init__.py
byuhbll_django_dry/admin.py
byuhbll_django_dry/auth.py
byuhbll_django_dry/logging.py
byuhbll_django_dry/loghandlers.py
byuhbll_django_dry/middleware.py
byuhbll_django_dry/models.py
byuhbll_django_dry/permissions.py
byuhbll_django_dry/settings.py
byuhbll_django_dry/signals.py
byuhbll_django_dry/urls.py
byuhbll_django_dry/utils.py
byuhbll_django_dry/views.py
byuhbll_django_dry/wsgi.py
byuhbll_django_dry/scripts/__init__.py
byuhbll_django_dry/scripts/cli.py
byuhbll_django_dry-1.1.0.dist-info/METADATA
byuhbll_django_dry-1.1.0.dist-info/WHEEL
byuhbll_django_dry-1.1.0.dist-info/entry_points.txt
byuhbll_django_dry-1.1.0.dist-info/licenses/LICENSE
byuhbll_django_dry-1.1.0.dist-info/RECORD
