Metadata-Version: 2.4
Name: byuhbll-django-dry
Version: 1.1.0
Summary: Reduce duplication and boilerplate in Django apps.
Project-URL: Homepage, https://gitlab.com/byuhbll/lib/python/django-dry
Project-URL: Source, https://gitlab.com/byuhbll/lib/python/django-dry
Author-email: BYU Library IT <byulibraryit@byu.edu>
License-Expression: BSD-3-Clause
License-File: LICENSE
Classifier: Framework :: Django
Classifier: Framework :: Django :: 3.2
Classifier: Framework :: Django :: 4.2
Classifier: Framework :: Django :: 5.2
Classifier: Intended Audience :: Developers
Classifier: License :: OSI Approved :: BSD License
Classifier: Operating System :: OS Independent
Classifier: Programming Language :: Python
Classifier: Programming Language :: Python :: 3
Classifier: Programming Language :: Python :: 3 :: Only
Classifier: Programming Language :: Python :: 3.8
Classifier: Programming Language :: Python :: 3.9
Classifier: Programming Language :: Python :: 3.10
Classifier: Programming Language :: Python :: 3.11
Classifier: Programming Language :: Python :: 3.12
Classifier: Programming Language :: Python :: 3.13
Requires-Python: >=3.8
Requires-Dist: byuhbll-configuro
Requires-Dist: click
Requires-Dist: colorlog
Requires-Dist: django
Requires-Dist: django-extensions>=2.2.8
Requires-Dist: django-filter
Requires-Dist: django-hijack>=3.0
Requires-Dist: djangorestframework
Requires-Dist: mozilla-django-oidc
Requires-Dist: pytz
Requires-Dist: requests
Requires-Dist: whitenoise
Provides-Extra: debug
Requires-Dist: django-debug-toolbar; extra == 'debug'
Provides-Extra: hbll
Requires-Dist: byuhbll-emporio; extra == 'hbll'
Requires-Dist: byuhbll-person-client; extra == 'hbll'
